data/__init__.py
hyper_butterfly/_C.cp311-win_amd64.pyd
hyper_butterfly/__init__.py
hyper_butterfly/hyper_butterfly_py.py
hyper_butterfly/csrc/butterfly.h
hyper_butterfly/csrc/butterfly_backend.h
hyper_butterfly/csrc/common_defs.h
hyper_butterfly/csrc/extension.cpp
hyper_butterfly/csrc/hyper_butterfly.h
hyper_butterfly/csrc/hyper_butterfly_cpu.cpp
hyper_butterfly/csrc/hyper_butterfly_cpu.h
hyper_butterfly/csrc/hyper_butterfly_cuda.cu
hyper_butterfly/csrc/maps.h
hyper_butterfly-0.1.0.dist-info/METADATA
hyper_butterfly-0.1.0.dist-info/WHEEL
hyper_butterfly-0.1.0.dist-info/top_level.txt
hyper_butterfly-0.1.0.dist-info/RECORD
